LICENSE.txt
README.txt
setup.py
src/archetypes/__init__.py
src/archetypes.clippingimage.egg-info/PKG-INFO
src/archetypes.clippingimage.egg-info/SOURCES.txt
src/archetypes.clippingimage.egg-info/dependency_links.txt
src/archetypes.clippingimage.egg-info/namespace_packages.txt
src/archetypes.clippingimage.egg-info/not-zip-safe
src/archetypes.clippingimage.egg-info/requires.txt
src/archetypes.clippingimage.egg-info/top_level.txt
src/archetypes/clippingimage/__init__.py
src/archetypes/clippingimage/_field.py
src/archetypes/clippingimage/blob.zcml
src/archetypes/clippingimage/patch.zcml
src/archetypes/clippingimage/utils.py