Metadata-Version: 1.0
Name: archetypes.clippingimage
Version: 2.1
Summary: Image field and/or patch with clipping support for Plone/Archetypes.
Home-page: https://svn.plone.org/svn/archetypes/MoreFieldsAndWidgets/archetypes.clippingimage
Author: Jens Klein
Author-email: jens@bluedynamics.com
License: BSD
Platform: UNKNOWN
Classifier: License :: OSI Approved :: BSD License
Classifier: Operating System :: OS Independent
Classifier: Programming Language :: Python
Classifier: Framework :: Zope2
Classifier: Framework :: Plone
Classifier: Intended Audience :: Developers
Classifier: Topic :: Software Development :: Libraries :: Python Modules
